__main__.py
elmolcs/__init__.py
elmolcs/constants.py
elmolcs/cscoll.py
elmolcs/filehandler.py
elmolcs/reader.py
elmolcs-0.0.1.dist-info/licenses/LICENSE
elmolcs-0.0.1.dist-info/METADATA
elmolcs-0.0.1.dist-info/WHEEL
elmolcs-0.0.1.dist-info/top_level.txt
elmolcs-0.0.1.dist-info/RECORD
