Metadata-Version: 2.4
Name: elmolcs
Version: 0.0.1
Summary: Package for reading and loading electron-molecule collision (differential) cross sections
Author-email: Anthony Jeseněk <anthony.schmalzried@mailfence.com>
License-Expression: GPL-3.0-or-later
Project-URL: Homepage, https://codeberg.org/aschmalz/elmolcs
Project-URL: Bug Tracker, https://codeberg.org/aschmalz/elmolcs/issues
Keywords: electron,cross section,reader
Classifier: Programming Language :: Python :: 3
Classifier: Operating System :: OS Independent
Requires-Python: >=3.7
License-File: LICENSE
Requires-Dist: numpy
Requires-Dist: bidict
Requires-Dist: aenum
Requires-Dist: numba
Requires-Dist: pandas
Requires-Dist: scipy
Requires-Dist: sortedcontainers
Requires-Dist: uncertainties
Dynamic: license-file
